camellia/__init__.py
camellia/verilog/__init__.py
camellia/verilog/block.py
camellia/verilog/bundle.py
camellia/verilog/exception.py
camellia/verilog/instance.py
camellia/verilog/module.py
camellia/verilog/rawcode.py
camellia-0.1.0.dist-info/METADATA
camellia-0.1.0.dist-info/WHEEL
camellia-0.1.0.dist-info/licenses/LICENSE
camellia-0.1.0.dist-info/RECORD
