Metadata-Version: 2.1
Name: camellia
Version: 0.1.0
Summary: A Python 3 library to speed up Verilog programming.
Author-email: Yiming Liu <artyomliu@hust.edu.cn>
License-File: LICENSE
Classifier: License :: OSI Approved :: MIT License
Classifier: Operating System :: OS Independent
Classifier: Programming Language :: Python :: 3
Requires-Python: >=3.7
